cudaq_solvers/__init__.py
cudaq_solvers/_pycudaqx_solvers_the_suffix_matters_cudaq_solvers.cpython-310-aarch64-linux-gnu.so
cudaq_solvers/bin/cudaq-pyscf
cudaq_solvers/gqe_algorithm/gqe.py
cudaq_solvers/gqe_algorithm/loss.py
cudaq_solvers/gqe_algorithm/transformer.py
cudaq_solvers/lib/libcudaq-solvers.so
cudaq_solvers/tools/molecule/pyscf/hamiltonian_generator.py
cudaq_solvers/tools/molecule/pyscf/generators/gas_phase_generator.py
cudaq_solvers-0.4.0.dist-info/METADATA
cudaq_solvers-0.4.0.dist-info/WHEEL
cudaq_solvers-0.4.0.dist-info/RECORD
