Metadata-Version: 2.2
Name: cudaq-solvers
Version: 0.4.0
Summary: Accelerated libraries for quantum-classical solvers built on CUDA-Q
Author: NVIDIA Corporation & Affiliates
Maintainer: NVIDIA Corporation & Affiliates
Classifier: Intended Audience :: Science/Research
Classifier: Intended Audience :: Developers
Classifier: Programming Language :: Python
Classifier: Programming Language :: Python :: 3
Classifier: Programming Language :: Python :: 3.10
Classifier: Programming Language :: Python :: 3.11
Classifier: Programming Language :: Python :: 3.12
Classifier: Programming Language :: Python :: 3.13
Classifier: Environment :: GPU :: NVIDIA CUDA
Classifier: Environment :: GPU :: NVIDIA CUDA :: 12
Classifier: Topic :: Software Development
Classifier: Topic :: Scientific/Engineering
Project-URL: Homepage, https://nvidia.github.io/cudaqx
Project-URL: Documentation, https://nvidia.github.io/cudaqx/components/solvers/introduction.html
Project-URL: Repository, https://github.com/NVIDIA/cudaqx
Requires-Python: >=3.10
Requires-Dist: cuda-quantum-cu12>=0.12
Requires-Dist: fastapi
Requires-Dist: networkx
Requires-Dist: pyscf
Requires-Dist: scipy
Requires-Dist: uvicorn
Provides-Extra: gqe
Requires-Dist: torch>=2.0.0; extra == "gqe"
Requires-Dist: lightning>=2.0.0; extra == "gqe"
Requires-Dist: ml_collections>=0.1.0; extra == "gqe"
Requires-Dist: mpi4py>=3.1.0; extra == "gqe"
Requires-Dist: transformers>=4.30.0; extra == "gqe"
